c_wm_dist.cpython-36m-x86_64-linux-gnu.so
wm_dist-1.0.2.dist-info/DESCRIPTION.rst
wm_dist-1.0.2.dist-info/METADATA
wm_dist-1.0.2.dist-info/RECORD
wm_dist-1.0.2.dist-info/WHEEL
wm_dist-1.0.2.dist-info/metadata.json
wm_dist-1.0.2.dist-info/top_level.txt
