Metadata-Version: 2.0
Name: wm-dist
Version: 1.0.2
Summary: Calculates distances through volume with Eikonal equation
Home-page: https://github.com/tfunck/wm_dist
Author: Thomas Funck
Author-email: tffunck@gmail.com
License: UNKNOWN
Platform: UNKNOWN
Classifier: Programming Language :: Python :: 3
Classifier: License :: OSI Approved :: MIT License
Classifier: Operating System :: OS Independent
